Lab2/ripple_adder/FA.vhdl
library ieee;
use ieee.std_logic_1164.all;

entity FA is 
  port (a, b, c_in : in std_logic;
        sum, carry : out std_logic
    );
end FA;

architecture arch of FA is

begin
  sum <= a xor b xor c_in; 
  carry <= (a and b) or (c_in and a) or (c_in and b) ;
end arch;

Lab2/nbit_ripple-carry_FullAdder/source.vhdl
library ieee;
use ieee.std_logic_1164.all;

entity ripple_carry_adder is
  generic (
    WIDTH : natural := 10
    );
  port (
    in_A  : in std_logic_vector(WIDTH downto 0);
    in_B  : in std_logic_vector(WIDTH downto 0);
    --
    result   : out std_logic_vector(WIDTH+1 downto 0)
    );
end ripple_carry_adder;
 
 
architecture rtl of ripple_carry_adder is

 
  signal C : std_logic_vector(WIDTH+1 downto 0);
  signal SUM   : std_logic_vector(WIDTH downto 0);
 
   
begin
 
  C(0) <= '0';                    -- no carry input on first full adder
   
  SET_WIDTH : for ii in 0 to WIDTH generate
    i_FULL_ADDER_INST : entity work.FA 
      port map (
        a  => in_A(ii),
        b  => in_B(ii),
        c_in => C(ii),
        sum   => SUM(ii),
        carry => C(ii+1)
        );
  end generate SET_WIDTH;
 
  result <= C(WIDTH) & SUM;  -- VHDL Concatenation
   
end rtl;

Lab2/nbit_ripple-carry_FullAdder/test_bench_proc.vhdl

library ieee;
use ieee.std_logic_1164.all;
use ieee.numeric_std.all;

--In this version of TB the design
--uses 2 for-loop cycle to generate
--the A and B input of the sum



entity ripple_adder_tb is
end ripple_adder_tb;

--In the declaration we put all the
--signals we need: the input output  
--of the DUT, and a time definition
architecture tb of ripple_adder_tb is
 constant WIDTH : natural := 10;
    signal a, b :std_logic_vector(WIDTH downto 0);--input

    signal result : std_logic_vector(WIDTH+1 downto 0);  -- output
    constant period: time := 1 ns; --time constant
   
begin
        -- connecting testbench signals with half_adder.vhd
	UUT : entity work.ripple_carry_adder port map (
		in_a => a,
		in_b => b,
		result => result
		);
process
--two concatenated for-loops generate all the addend combinations 
	begin
	for ia in 0 to ((WIDTH**2)-1) loop
		a<=std_logic_vector(to_unsigned(ia,WIDTH+1));
		for ib in 0 to ((WIDTH**2)-1) loop	
			b<=std_logic_vector(to_unsigned(ib,WIDTH+1));
			wait for period;
		end loop;
	end loop;
end process;
             
          
end tb ;

Lab2/nbit_ripple-carry_FullAdder/waves.vcd
$date
  Sun Nov 29 15:58:26 2020
$end
$version
  GHDL v0
$end
$timescale
  1 fs
$end
$scope module standard $end
$upscope $end
$scope module std_logic_1164 $end
$upscope $end
$scope module numeric_std $end
$upscope $end
$scope module ripple_adder_tb $end
$var reg 11 ! a[10:0] $end
$var reg 11 " b[10:0] $end
$var reg 12 # result[11:0] $end
$scope module uut $end
$var reg 11 $ in_a[10:0] $end
$var reg 11 % in_b[10:0] $end
$var reg 12 & result[11:0] $end
$var reg 12 ' c[11:0] $end
$var reg 11 ( sum[10:0] $end
$scope module set_width(0) $end
$scope module i_full_adder_inst $end
$var reg 1 ) a $end
$var reg 1 * b $end
$var reg 1 + c_in $end
$var reg 1 , sum $end
$var reg 1 - carry $end
$upscope $end
$upscope $end
$scope module set_width(1) $end
$scope module i_full_adder_inst $end
$var reg 1 . a $end
$var reg 1 / b $end
$var reg 1 0 c_in $end
$var reg 1 1 sum $end
$var reg 1 2 carry $end
$upscope $end
$upscope $end
$scope module set_width(2) $end
$scope module i_full_adder_inst $end
$var reg 1 3 a $end
$var reg 1 4 b $end
$var reg 1 5 c_in $end
$var reg 1 6 sum $end
$var reg 1 7 carry $end
$upscope $end
$upscope $end
$scope module set_width(3) $end
$scope module i_full_adder_inst $end
$var reg 1 8 a $end
$var reg 1 9 b $end
$var reg 1 : c_in $end
$var reg 1 ; sum $end
$var reg 1 < carry $end
$upscope $end
$upscope $end
$scope module set_width(4) $end
$scope module i_full_adder_inst $end
$var reg 1 = a $end
$var reg 1 > b $end
$var reg 1 ? c_in $end
$var reg 1 @ sum $end
$var reg 1 A carry $end
$upscope $end
$upscope $end
$scope module set_width(5) $end
$scope module i_full_adder_inst $end
$var reg 1 B a $end
$var reg 1 C b $end
$var reg 1 D c_in $end
$var reg 1 E sum $end
$var reg 1 F carry $end
$upscope $end
$upscope $end
$scope module set_width(6) $end
$scope module i_full_adder_inst $end
$var reg 1 G a $end
$var reg 1 H b $end
$var reg 1 I c_in $end
$var reg 1 J sum $end
$var reg 1 K carry $end
$upscope $end
$upscope $end
$scope module set_width(7) $end
$scope module i_full_adder_inst $end
$var reg 1 L a $end
$var reg 1 M b $end
$var reg 1 N c_in $end
$var reg 1 O sum $end
$var reg 1 P carry $end
$upscope $end
$upscope $end
$scope module set_width(8) $end
$scope module i_full_adder_inst $end
$var reg 1 Q a $end
$var reg 1 R b $end
$var reg 1 S c_in $end
$var reg 1 T sum $end
$var reg 1 U carry $end
$upscope $end
$upscope $end
$scope module set_width(9) $end
$scope module i_full_adder_inst $end
$var reg 1 V a $end
$var reg 1 W b $end
$var reg 1 X c_in $end
$var reg 1 Y sum $end
$var reg 1 Z carry $end
$upscope $end
$upscope $end
$scope module set_width(10) $end
$scope module i_full_adder_inst $end
$var reg 1 [ a $end
$var reg 1 \ b $end
$var reg 1 ] c_in $end
$var reg 1 ^ sum $end
$var reg 1 _ carry $end
$upscope $end
$upscope $end
$upscope $end
$upscope $end
$enddefinitions $end
#0
b00000000000 !
b00000000000 "
b000000000000 #
b00000000000 $
b00000000000 %
b000000000000 &
b000000000000 '
b00000000000 (
0)
0*
0+
0,
0-
0.
0/
00
01
02
03
04
05
06
07
08
09
0:
0;
0<
0=
0>
0?
0@
0A
0B
0C
0D
0E
0F
0G
0H
0I
0J
0K
0L
0M
0N
0O
0P
0Q
0R
0S
0T
0U
0V
0W
0X
0Y
0Z
0[
0\
0]
0^
0_
#1000000
b00000000001 "
b000000000001 #
b00000000001 %
b000000000001 &
b00000000001 (
1*
1,
#2000000
b00000000010 "
b000000000010 #
b00000000010 %
b000000000010 &
b00000000010 (
0*
0,
1/
11
#3000000
b00000000011 "
b000000000011 #
b00000000011 %
b000000000011 &
b00000000011 (
1*
1,
#4000000
b00000000100 "
b000000000100 #
b00000000100 %
b000000000100 &
b00000000100 (
0*
0,
0/
01
14
16
#5000000
b00000000101 "
b000000000101 #
b00000000101 %
b000000000101 &
b00000000101 (
1*
1,
#6000000
b00000000110 "
b000000000110 #
b00000000110 %
b000000000110 &
b00000000110 (
0*
0,
1/
11
#7000000
b00000000111 "
b000000000111 #
b00000000111 %
b000000000111 &
b00000000111 (
1*
1,
#8000000
b00000001000 "
b000000001000 #
b00000001000 %
b000000001000 &
b00000001000 (
0*
0,
0/
01
04
06
19
1;
#9000000
b00000001001 "
b000000001001 #
b00000001001 %
b000000001001 &
b00000001001 (
1*
1,
#10000000
b00000001010 "
b000000001010 #
b00000001010 %
b000000001010 &
b00000001010 (
0*
0,
1/
11
#11000000
b00000001011 "
b000000001011 #
b00000001011 %
b000000001011 &
b00000001011 (
1*
1,
#12000000
b00000001100 "
b000000001100 #
b00000001100 %
b000000001100 &
b00000001100 (
0*
0,
0/
01
14
16
#13000000
b00000001101 "
b000000001101 #
b00000001101 %
b000000001101 &
b00000001101 (
1*
1,
#14000000
b00000001110 "
b000000001110 #
b00000001110 %
b000000001110 &
b00000001110 (
0*
0,
1/
11
#15000000
b00000001111 "
b000000001111 #
b00000001111 %
b000000001111 &
b00000001111 (
1*
1,
#16000000
b00000010000 "
b000000010000 #
b00000010000 %
b000000010000 &
b00000010000 (
0*
0,
0/
01
04
06
09
0;
1>
1@
#17000000
b00000010001 "
b000000010001 #
b00000010001 %
b000000010001 &
b00000010001 (
1*
1,
#18000000
b00000010010 "
b000000010010 #
b00000010010 %
b000000010010 &
b00000010010 (
0*
0,
1/
11
#19000000
b00000010011 "
b000000010011 #
b00000010011 %
b000000010011 &
b00000010011 (
1*
1,
#20000000
b00000010100 "
b000000010100 #
b00000010100 %
b000000010100 &
b00000010100 (
0*
0,
0/
01
14
16
#21000000
b00000010101 "
b000000010101 #
b00000010101 %
b000000010101 &
b00000010101 (
1*
1,
#22000000
b00000010110 "
b000000010110 #
b00000010110 %
b000000010110 &
b00000010110 (
0*
0,
1/
11
#23000000
b00000010111 "
b000000010111 #
b00000010111 %
b000000010111 &
b00000010111 (
1*
1,
#24000000
b00000011000 "
b000000011000 #
b00000011000 %
b000000011000 &
b00000011000 (
0*
0,
0/
01
04
06
19
1;
#25000000
b00000011001 "
b000000011001 #
b00000011001 %
b000000011001 &
b00000011001 (
1*
1,
#26000000
b00000011010 "
b000000011010 #
b00000011010 %
b000000011010 &
b00000011010 (
0*
0,
1/
11
#27000000
b00000011011 "
b000000011011 #
b00000011011 %
b000000011011 &
b00000011011 (
1*
1,
#28000000
b00000011100 "
b000000011100 #
b00000011100 %
b000000011100 &
b00000011100 (
0*
0,
0/
01
14
16
#29000000
b00000011101 "
b000000011101 #
b00000011101 %
b000000011101 &
b00000011101 (
1*
1,
#30000000
b00000011110 "
b000000011110 #
b00000011110 %
b000000011110 &
b00000011110 (
0*
0,
1/
11
#31000000
b00000011111 "
b000000011111 #
b00000011111 %
b000000011111 &
b00000011111 (
1*
1,
#32000000
b00000100000 "
b000000100000 #
b00000100000 %
b000000100000 &
b00000100000 (
0*
0,
0/
01
04
06
09
0;
0>
0@
1C
1E
#33000000
b00000100001 "
b000000100001 #
b00000100001 %
b000000100001 &
b00000100001 (
1*
1,
#34000000
b00000100010 "
b000000100010 #
b00000100010 %
b000000100010 &
b00000100010 (
0*
0,
1/
11
#35000000
b00000100011 "
b000000100011 #
b00000100011 %
b000000100011 &
b00000100011 (
1*
1,
#36000000
b00000100100 "
b000000100100 #
b00000100100 %
b000000100100 &
b00000100100 (
0*
0,
0/
01
14
16
#37000000
b00000100101 "
b000000100101 #
b00000100101 %
b000000100101 &
b00000100101 (
1*
1,
#38000000
b00000100110 "
b000000100110 #
b00000100110 %
b000000100110 &
b00000100110 (
0*
0,
1/
11
#39000000
b00000100111 "
b000000100111 #
b00000100111 %
b000000100111 &
b00000100111 (
1*
1,
#40000000
b00000101000 "
b000000101000 #
b00000101000 %
b000000101000 &
b00000101000 (
0*
0,
0/
01
04
06
19
1;
#41000000
b00000101001 "
b000000101001 #
b00000101001 %
b000000101001 &
b00000101001 (
1*
1,
#42000000
b00000101010 "
b000000101010 #
b00000101010 %
b000000101010 &
b00000101010 (
0*
0,
1/
11
#43000000
b00000101011 "
b000000101011 #
b00000101011 %
b000000101011 &
b00000101011 (
1*
1,
#44000000
b00000101100 "
b000000101100 #
b00000101100 %
b000000101100 &
b00000101100 (
0*
0,
0/
01
14
16
#45000000
b00000101101 "
b000000101101 #
b00000101101 %
b000000101101 &
b00000101101 (
1*
1,
#46000000
b00000101110 "
b000000101110 #
b00000101110 %
b000000101110 &
b00000101110 (
0*
0,
1/
11
#47000000
b00000101111 "
b000000101111 #
b00000101111 %
b000000101111 &
b00000101111 (
1*
1,
#48000000
b00000110000 "
b000000110000 #
b00000110000 %
b000000110000 &
b00000110000 (
0*
0,
0/
01
04
06
09
0;
1>
1@
#49000000
b00000110001 "
b000000110001 #
b00000110001 %
b000000110001 &
b00000110001 (
1*
1,
#50000000
b00000110010 "
b000000110010 #
b00000110010 %
b000000110010 &
b00000110010 (
0*
0,
1/
11
#51000000
b00000110011 "
b000000110011 #
b00000110011 %
b000000110011 &
b00000110011 (
1*
1,
#52000000
b00000110100 "
b000000110100 #
b00000110100 %
b000000110100 &
b00000110100 (
0*
0,
0/
01
14
16
#53000000
b00000110101 "
b000000110101 #
b00000110101 %
b000000110101 &
b00000110101 (
1*
1,
#54000000
b00000110110 "
b000000110110 #
b00000110110 %
b000000110110 &
b00000110110 (
0*
0,
1/
11
#55000000
b00000110111 "
b000000110111 #
b00000110111 %
b000000110111 &
b00000110111 (
1*
1,
#56000000
b00000111000 "
b000000111000 #
b00000111000 %
b000000111000 &
b00000111000 (
0*
0,
0/
01
04
06
19
1;
#57000000
b00000111001 "
b000000111001 #
b00000111001 %
b000000111001 &
b00000111001 (
1*
1,
#58000000
b00000111010 "
b000000111010 #
b00000111010 %
b000000111010 &
b00000111010 (
0*
0,
1/
11
#59000000
b00000111011 "
b000000111011 #
b00000111011 %
b000000111011 &
b00000111011 (
1*
1,
#60000000
b00000111100 "
b000000111100 #
b00000111100 %
b000000111100 &
b00000111100 (
0*
0,
0/
01
14
16
#61000000
b00000111101 "
b000000111101 #
b00000111101 %
b000000111101 &
b00000111101 (
1*
1,
#62000000
b00000111110 "
b000000111110 #
b00000111110 %
b000000111110 &
b00000111110 (
0*
0,
1/
11
#63000000
b00000111111 "
b000000111111 #
b00000111111 %
b000000111111 &
b00000111111 (
1*
1,
#64000000
b00001000000 "
b000001000000 #
b00001000000 %
b000001000000 &
b00001000000 (
0*
0,
0/
01
04
06
09
0;
0>
0@
0C
0E
1H
1J
#65000000
b00001000001 "
b000001000001 #
b00001000001 %
b000001000001 &
b00001000001 (
1*
1,
#66000000
b00001000010 "
b000001000010 #
b00001000010 %
b000001000010 &
b00001000010 (
0*
0,
1/
11
#67000000
b00001000011 "
b000001000011 #
b00001000011 %
b000001000011 &
b00001000011 (
1*
1,
#68000000
b00001000100 "
b000001000100 #
b00001000100 %
b000001000100 &
b00001000100 (
0*
0,
0/
01
14
16
#69000000
b00001000101 "
b000001000101 #
b00001000101 %
b000001000101 &
b00001000101 (
1*
1,
#70000000
b00001000110 "
b000001000110 #
b00001000110 %
b000001000110 &
b00001000110 (
0*
0,
1/
11
#71000000
b00001000111 "
b000001000111 #
b00001000111 %
b000001000111 &
b00001000111 (
1*
1,
#72000000
b00001001000 "
b000001001000 #
b00001001000 %
b000001001000 &
b00001001000 (
0*
0,
0/
01
04
06
19
1;
#73000000
b00001001001 "
b000001001001 #
b00001001001 %
b000001001001 &
b00001001001 (
1*
1,
#74000000
b00001001010 "
b000001001010 #
b00001001010 %
b000001001010 &
b00001001010 (
0*
0,
1/
11
#75000000
b00001001011 "
b000001001011 #
b00001001011 %
b000001001011 &
b00001001011 (
1*
1,
#76000000
b00001001100 "
b000001001100 #
b00001001100 %
b000001001100 &
b00001001100 (
0*
0,
0/
01
14
16
#77000000
b00001001101 "
b000001001101 #
b00001001101 %
b000001001101 &
b00001001101 (
1*
1,
#78000000
b00001001110 "
b000001001110 #
b00001001110 %
b000001001110 &
b00001001110 (
0*
0,
1/
11
#79000000
b00001001111 "
b000001001111 #
b00001001111 %
b000001001111 &
b00001001111 (
1*
1,
#80000000
b00001010000 "
b000001010000 #
b00001010000 %
b000001010000 &
b00001010000 (
0*
0,
0/
01
04
06
09
0;
1>
1@
#81000000
b00001010001 "
b000001010001 #
b00001010001 %
b000001010001 &
b00001010001 (
1*
1,
#82000000
b00001010010 "
b000001010010 #
b00001010010 %
b000001010010 &
b00001010010 (
0*
0,
1/
11
#83000000
b00001010011 "
b000001010011 #
b00001010011 %
b000001010011 &
b00001010011 (
1*
1,
#84000000
b00001010100 "
b000001010100 #
b00001010100 %
b000001010100 &
b00001010100 (
0*
0,
0/
01
14
16
#85000000
b00001010101 "
b000001010101 #
b00001010101 %
b000001010101 &
b00001010101 (
1*
1,
#86000000
b00001010110 "
b000001010110 #
b00001010110 %
b000001010110 &
b00001010110 (
0*
0,
1/
11
#87000000
b00001010111 "
b000001010111 #
b00001010111 %
b000001010111 &
b00001010111 (
1*
1,
#88000000
b00001011000 "
b000001011000 #
b00001011000 %
b000001011000 &
b00001011000 (
0*
0,
0/
01
04
06
19
1;
#89000000
b00001011001 "
b000001011001 #
b00001011001 %
b000001011001 &
b00001011001 (
1*
1,
#90000000
b00001011010 "
b000001011010 #
b00001011010 %
b000001011010 &
b00001011010 (
0*
0,
1/
11
#91000000
b00001011011 "
b000001011011 #
b00001011011 %
b000001011011 &
b00001011011 (
1*
1,
#92000000
b00001011100 "
b000001011100 #
b00001011100 %
b000001011100 &
b00001011100 (
0*
0,
0/
01
14
16
#93000000
b00001011101 "
b000001011101 #
b00001011101 %
b000001011101 &
b00001011101 (
1*
1,
#94000000
b00001011110 "
b000001011110 #
b00001011110 %
b000001011110 &
b00001011110 (
0*
0,
1/
11
#95000000
b00001011111 "
b000001011111 #
b00001011111 %
b000001011111 &
b00001011111 (
1*
1,
#96000000
b00001100000 "
b000001100000 #
b00001100000 %
b000001100000 &
b00001100000 (
0*
0,
0/
01
04
06
09
0;
0>
0@
1C
1E
#97000000
b00001100001 "
b000001100001 #
b00001100001 %
b000001100001 &
b00001100001 (
1*
1,
#98000000
b00001100010 "
b000001100010 #
b00001100010 %
b000001100010 &
b00001100010 (
0*
0,
1/
11
#99000000
b00001100011 "
b000001100011 #
b00001100011 %
b000001100011 &
b00001100011 (
1*
1,
#100000000
b00000000001 !
b00000000000 "
b000000000001 #
b00000000001 $
b00000000000 %
b000000000001 &
b00000000001 (
1)
0*
0/
01
0C
0E
0H
0J
#101000000
b00000000001 "
b000000000010 #
b00000000001 %
b000000000010 &
b000000000010 '
b00000000010 (
1*
0,
1-
10
11
#102000000
b00000000010 "
b000000000011 #
b00000000010 %
b000000000011 &
b000000000000 '
b00000000011 (
0*
1,
0-
1/
00
11
02
05
06
#103000000
b00000000011 "
b000000000100 #
b00000000011 %
b000000000100 &
b000000000110 '
b00000000100 (
1*
0,
1-
10
01
12
15
16
#104000000
b00000000100 "
b000000000101 #
b00000000100 %
b000000000101 &
b000000000000 '
b00000000101 (
0*
1,
0-
0/
00
01
02
14
05
16
07
0:
0;
#105000000
b00000000101 "
b000000000110 #
b00000000101 %
b000000000110 &
b000000000010 '
b00000000110 (
1*
0,
1-
10
11
#106000000
b00000000110 "
b000000000111 #
b00000000110 %
b000000000111 &
b000000000000 '
b00000000111 (
0*
1,
0-
1/
00
11
02
05
16
07
0:
0;
#107000000
b00000000111 "
b000000001000 #
b00000000111 %
b000000001000 &
b000000001110 '
b00000001000 (
1*
0,
1-
10
01
12
15
06
17
1:
1;
#108000000
b00000001000 "
b000000001001 #
b00000001000 %
b000000001001 &
b000000000000 '
b00000001001 (
0*
1,
0-
0/
00
01
02
04
05
06
07
19
0:
1;
0<
0?
0@
#109000000
b00000001001 "
b000000001010 #
b00000001001 %
b000000001010 &
b000000000010 '
b00000001010 (
1*
0,
1-
10
11
#110000000
b00000001010 "
b000000001011 #
b00000001010 %
b000000001011 &
b000000000000 '
b00000001011 (
0*
1,
0-
1/
00
11
02
05
06
#111000000
b00000001011 "
b000000001100 #
b00000001011 %
b000000001100 &
b000000000110 '
b00000001100 (
1*
0,
1-
10
01
12
15
16
#112000000
b00000001100 "
b000000001101 #
b00000001100 %
b000000001101 &
b000000000000 '
b00000001101 (
0*
1,
0-
0/
00
01
02
14
05
16
07
0:
1;
0<
0?
0@
#113000000
b00000001101 "
b000000001110 #
b00000001101 %
b000000001110 &
b000000000010 '
b00000001110 (
1*
0,
1-
10
11
#114000000
b00000001110 "
b000000001111 #
b00000001110 %
b000000001111 &
b000000000000 '
b00000001111 (
0*
1,
0-
1/
00
11
02
05
16
07
0:
1;
0<
0?
0@
#115000000
b00000001111 "
b000000010000 #
b00000001111 %
b000000010000 &
b000000011110 '
b00000010000 (
1*
0,
1-
10
01
12
15
06
17
1:
0;
1<
1?
1@
#116000000
b00000010000 "
b000000010001 #
b00000010000 %
b000000010001 &
b000000000000 '
b00000010001 (
0*
1,
0-
0/
00
01
02
04
05
06
07
09
0:
0;
0<
1>
0?
1@
0A
0D
0E
#117000000
b00000010001 "
b000000010010 #
b00000010001 %
b000000010010 &
b000000000010 '
b00000010010 (
1*
0,
1-
10
11
#118000000
b00000010010 "
b000000010011 #
b00000010010 %
b000000010011 &
b000000000000 '
b00000010011 (
0*
1,
0-
1/
00
11
02
05
06
#119000000
b00000010011 "
b000000010100 #
b00000010011 %
b000000010100 &
b000000000110 '
b00000010100 (
1*
0,
1-
10
01
12
15
16
#120000000
b00000010100 "
b000000010101 #
b00000010100 %
b000000010101 &
b000000000000 '
b00000010101 (
0*
1,
0-
0/
00
01
02
14
05
16
07
0:
0;
#121000000
b00000010101 "
b000000010110 #
b00000010101 %
b000000010110 &
b000000000010 '
b00000010110 (
1*
0,
1-
10
11
#122000000
b00000010110 "
b000000010111 #
b00000010110 %
b000000010111 &
b000000000000 '
b00000010111 (
0*
1,
0-
1/
00
11
02
05
16
07
0:
0;
#123000000
b00000010111 "
b000000011000 #
b00000010111 %
b000000011000 &
b000000001110 '
b00000011000 (
1*
0,
1-
10
01
12
15
06
17
1:
1;
#124000000
b00000011000 "
b000000011001 #
b00000011000 %
b000000011001 &
b000000000000 '
b00000011001 (
0*
1,
0-
0/
00
01
02
04
05
06
07
19
0:
1;
0<
0?
1@
0A
0D
0E
#125000000
b00000011001 "
b000000011010 #
b00000011001 %
b000000011010 &
b000000000010 '
b00000011010 (
1*
0,
1-
10
11
#126000000
b00000011010 "
b000000011011 #
b00000011010 %
b000000011011 &
b000000000000 '
b00000011011 (
0*
1,
0-
1/
00
11
02
05
06
#127000000
b00000011011 "
b000000011100 #
b00000011011 %
b000000011100 &
b000000000110 '
b00000011100 (
1*
0,
1-
10
01
12
15
16
#128000000
b00000011100 "
b000000011101 #
b00000011100 %
b000000011101 &
b000000000000 '
b00000011101 (
0*
1,
0-
0/
00
01
02
14
05
16
07
0:
1;
0<
0?
1@
0A
0D
0E
#129000000
b00000011101 "
b000000011110 #
b00000011101 %
b000000011110 &
b000000000010 '
b00000011110 (
1*
0,
1-
10
11
#130000000
b00000011110 "
b000000011111 #
b00000011110 %
b000000011111 &
b000000000000 '
b00000011111 (
0*
1,
0-
1/
00
11
02
05
16
07
0:
1;
0<
0?
1@
0A
0D
0E
#131000000
b00000011111 "
b000000100000 #
b00000011111 %
b000000100000 &
b000000111110 '
b00000100000 (
1*
0,
1-
10
01
12
15
06
17
1:
0;
1<
1?
0@
1A
1D
1E
#132000000
b00000100000 "
b000000100001 #
b00000100000 %
b000000100001 &
b000000000000 '
b00000100001 (
0*
1,
0-
0/
00
01
02
04
05
06
07
09
0:
0;
0<
0>
0?
0@
0A
1C
0D
1E
0F
0I
0J
#133000000
b00000100001 "
b000000100010 #
b00000100001 %
b000000100010 &
b000000000010 '
b00000100010 (
1*
0,
1-
10
11
#134000000
b00000100010 "
b000000100011 #
b00000100010 %
b000000100011 &
b000000000000 '
b00000100011 (
0*
1,
0-
1/
00
11
02
05
06
#135000000
b00000100011 "
b000000100100 #
b00000100011 %
b000000100100 &
b000000000110 '
b00000100100 (
1*
0,
1-
10
01
12
15
16
#136000000
b00000100100 "
b000000100101 #
b00000100100 %
b000000100101 &
b000000000000 '
b00000100101 (
0*
1,
0-
0/
00
01
02
14
05
16
07
0:
0;
#137000000
b00000100101 "
b000000100110 #
b00000100101 %
b000000100110 &
b000000000010 '
b00000100110 (
1*
0,
1-
10
11
#138000000
b00000100110 "
b000000100111 #
b00000100110 %
b000000100111 &
b000000000000 '
b00000100111 (
0*
1,
0-
1/
00
11
02
05
16
07
0:
0;
#139000000
b00000100111 "
b000000101000 #
b00000100111 %
b000000101000 &
b000000001110 '
b00000101000 (
1*
0,
1-
10
01
12
15
06
17
1:
1;
#140000000
b00000101000 "
b000000101001 #
b00000101000 %
b000000101001 &
b000000000000 '
b00000101001 (
0*
1,
0-
0/
00
01
02
04
05
06
07
19
0:
1;
0<
0?
0@
#141000000
b00000101001 "
b000000101010 #
b00000101001 %
b000000101010 &
b000000000010 '
b00000101010 (
1*
0,
1-
10
11
#142000000
b00000101010 "
b000000101011 #
b00000101010 %
b000000101011 &
b000000000000 '
b00000101011 (
0*
1,
0-
1/
00
11
02
05
06
#143000000
b00000101011 "
b000000101100 #
b00000101011 %
b000000101100 &
b000000000110 '
b00000101100 (
1*
0,
1-
10
01
12
15
16
#144000000
b00000101100 "
b000000101101 #
b00000101100 %
b000000101101 &
b000000000000 '
b00000101101 (
0*
1,
0-
0/
00
01
02
14
05
16
07
0:
1;
0<
0?
0@
#145000000
b00000101101 "
b000000101110 #
b00000101101 %
b000000101110 &
b000000000010 '
b00000101110 (
1*
0,
1-
10
11
#146000000
b00000101110 "
b000000101111 #
b00000101110 %
b000000101111 &
b000000000000 '
b00000101111 (
0*
1,
0-
1/
00
11
02
05
16
07
0:
1;
0<
0?
0@
#147000000
b00000101111 "
b000000110000 #
b00000101111 %
b000000110000 &
b000000011110 '
b00000110000 (
1*
0,
1-
10
01
12
15
06
17
1:
0;
1<
1?
1@
#148000000
b00000110000 "
b000000110001 #
b00000110000 %
b000000110001 &
b000000000000 '
b00000110001 (
0*
1,
0-
0/
00
01
02
04
05
06
07
09
0:
0;
0<
1>
0?
1@
0A
0D
1E
0F
0I
0J
#149000000
b00000110001 "
b000000110010 #
b00000110001 %
b000000110010 &
b000000000010 '
b00000110010 (
1*
0,
1-
10
11
#150000000
b00000110010 "
b000000110011 #
b00000110010 %
b000000110011 &
b000000000000 '
b00000110011 (
0*
1,
0-
1/
00
11
02
05
06
#151000000
b00000110011 "
b000000110100 #
b00000110011 %
b000000110100 &
b000000000110 '
b00000110100 (
1*
0,
1-
10
01
12
15
16
#152000000
b00000110100 "
b000000110101 #
b00000110100 %
b000000110101 &
b000000000000 '
b00000110101 (
0*
1,
0-
0/
00
01
02
14
05
16
07
0:
0;
#153000000
b00000110101 "
b000000110110 #
b00000110101 %
b000000110110 &
b000000000010 '
b00000110110 (
1*
0,
1-
10
11
#154000000
b00000110110 "
b000000110111 #
b00000110110 %
b000000110111 &
b000000000000 '
b00000110111 (
0*
1,
0-
1/
00
11
02
05
16
07
0:
0;
#155000000
b00000110111 "
b000000111000 #
b00000110111 %
b000000111000 &
b000000001110 '
b00000111000 (
1*
0,
1-
10
01
12
15
06
17
1:
1;
#156000000
b00000111000 "
b000000111001 #
b00000111000 %
b000000111001 &
b000000000000 '
b00000111001 (
0*
1,
0-
0/
00
01
02
04
05
06
07
19
0:
1;
0<
0?
1@
0A
0D
1E
0F
0I
0J
#157000000
b00000111001 "
b000000111010 #
b00000111001 %
b000000111010 &
b000000000010 '
b00000111010 (
1*
0,
1-
10
11
#158000000
b00000111010 "
b000000111011 #
b00000111010 %
b000000111011 &
b000000000000 '
b00000111011 (
0*
1,
0-
1/
00
11
02
05
06
#159000000
b00000111011 "
b000000111100 #
b00000111011 %
b000000111100 &
b000000000110 '
b00000111100 (
1*
0,
1-
10
01
12
15
16
#160000000
b00000111100 "
b000000111101 #
b00000111100 %
b000000111101 &
b000000000000 '
b00000111101 (
0*
1,
0-
0/
00
01
02
14
05
16
07
0:
1;
0<
0?
1@
0A
0D
1E
0F
0I
0J
#161000000
b00000111101 "
b000000111110 #
b00000111101 %
b000000111110 &
b000000000010 '
b00000111110 (
1*
0,
1-
10
11
#162000000
b00000111110 "
b000000111111 #
b00000111110 %
b000000111111 &
b000000000000 '
b00000111111 (
0*
1,
0-
1/
00
11
02
05
16
07
0:
1;
0<
0?
1@
0A
0D
1E
0F
0I
0J
#163000000
b00000111111 "
b000001000000 #
b00000111111 %
b000001000000 &
b000001111110 '
b00001000000 (
1*
0,
1-
10
01
12
15
06
17
1:
0;
1<
1?
0@
1A
1D
0E
1F
1I
1J
#164000000
b00001000000 "
b000001000001 #
b00001000000 %
b000001000001 &
b000000000000 '
b00001000001 (
0*
1,
0-
0/
00
01
02
04
05
06
07
09
0:
0;
0<
0>
0?
0@
0A
0C
0D
0E
0F
1H
0I
1J
0K
0N
0O
#165000000
b00001000001 "
b000001000010 #
b00001000001 %
b000001000010 &
b000000000010 '
b00001000010 (
1*
0,
1-
10
11
#166000000
b00001000010 "
b000001000011 #
b00001000010 %
b000001000011 &
b000000000000 '
b00001000011 (
0*
1,
0-
1/
00
11
02
05
06
#167000000
b00001000011 "
b000001000100 #
b00001000011 %
b000001000100 &
b000000000110 '
b00001000100 (
1*
0,
1-
10
01
12
15
16
#168000000
b00001000100 "
b000001000101 #
b00001000100 %
b000001000101 &
b000000000000 '
b00001000101 (
0*
1,
0-
0/
00
01
02
14
05
16
07
0:
0;
#169000000
b00001000101 "
b000001000110 #
b00001000101 %
b000001000110 &
b000000000010 '
b00001000110 (
1*
0,
1-
10
11
#170000000
b00001000110 "
b000001000111 #
b00001000110 %
b000001000111 &
b000000000000 '
b00001000111 (
0*
1,
0-
1/
00
11
02
05
16
07
0:
0;
#171000000
b00001000111 "
b000001001000 #
b00001000111 %
b000001001000 &
b000000001110 '
b00001001000 (
1*
0,
1-
10
01
12
15
06
17
1:
1;
#172000000
b00001001000 "
b000001001001 #
b00001001000 %
b000001001001 &
b000000000000 '
b00001001001 (
0*
1,
0-
0/
00
01
02
04
05
06
07
19
0:
1;
0<
0?
0@
#173000000
b00001001001 "
b000001001010 #
b00001001001 %
b000001001010 &
b000000000010 '
b00001001010 (
1*
0,
1-
10
11
#174000000
b00001001010 "
b000001001011 #
b00001001010 %
b000001001011 &
b000000000000 '
b00001001011 (
0*
1,
0-
1/
00
11
02
05
06
#175000000
b00001001011 "
b000001001100 #
b00001001011 %
b000001001100 &
b000000000110 '
b00001001100 (
1*
0,
1-
10
01
12
15
16
#176000000
b00001001100 "
b000001001101 #
b00001001100 %
b000001001101 &
b000000000000 '
b00001001101 (
0*
1,
0-
0/
00
01
02
14
05
16
07
0:
1;
0<
0?
0@
#177000000
b00001001101 "
b000001001110 #
b00001001101 %
b000001001110 &
b000000000010 '
b00001001110 (
1*
0,
1-
10
11
#178000000
b00001001110 "
b000001001111 #
b00001001110 %
b000001001111 &
b000000000000 '
b00001001111 (
0*
1,
0-
1/
00
11
02
05
16
07
0:
1;
0<
0?
0@
#179000000
b00001001111 "
b000001010000 #
b00001001111 %
b000001010000 &
b000000011110 '
b00001010000 (
1*
0,
1-
10
01
12
15
06
17
1:
0;
1<
1?
1@
