Lab1/clocked_full_adder/source.vhdl
library ieee;
use ieee.std_logic_1164.all;

entity full_adder is 
  port (a, b, clk, c_in : in std_logic;
        sum, carry : out std_logic
    );
end full_adder;

architecture arch of full_adder is

begin
process(clk)
begin
if(rising_edge(clk)) then
  sum <= a xor b xor c_in; 
  carry <= (a and b) or (c_in and a) or (c_in and b) ;
end if;
end process;
end arch;

Lab1/clocked_full_adder/test_bench.vhdl
-- clocked_full_adder_tb.vhd

library ieee;
use ieee.std_logic_1164.all;


entity clocked_full_adder_tb is
end clocked_full_adder_tb;

architecture tb of clocked_full_adder_tb is
    signal a, b, c_in : std_logic;  -- inputs 
    signal clk: std_logic :='0';
    signal sum, carry : std_logic;  -- outputs
begin
    -- connecting testbench signals with half_adder.vhd
    UUT : entity work.full_adder port map (
    	c_in=>c_in,
	clk =>clk,
	a => a,
	b => b,
	sum => sum,
	carry => carry);
	clk<=not clk after 5 ns;
tb1 : process
        constant period: time := 10 ns;
        begin
            a <= '0';
            b <= '0';
            c_in <= '0';
            wait for period;
            a <= '1';
            b <= '0';
            c_in <= '0';
            wait for period;
            a <= '0';
            b <= '1';
            c_in <= '0';
            wait for period;
            a <= '1';
            b <= '1';
            c_in <= '0';
            wait for period;
            a <= '0';
            b <= '0';
            c_in <= '1';
            wait for period;
            a <= '1';
            b <= '0';
            c_in <= '1';
            wait for period;  
            a <= '1';
            b <= '1';
            c_in <= '1';
            wait for period;            
            wait; -- indefinitely suspend process
        end process;
end tb ;

Lab1/clocked_full_adder/waves.vcd
$date
  Wed Nov 25 12:37:39 2020
$end
$version
  GHDL v0
$end
$timescale
  1 fs
$end
$scope module standard $end
$upscope $end
$scope module std_logic_1164 $end
$upscope $end
$scope module clocked_full_adder_tb $end
$var reg 1 ! a $end
$var reg 1 " b $end
$var reg 1 # c_in $end
$var reg 1 $ clk $end
$var reg 1 % sum $end
$var reg 1 & carry $end
$scope module uut $end
$var reg 1 ' a $end
$var reg 1 ( b $end
$var reg 1 ) clk $end
$var reg 1 * c_in $end
$var reg 1 + sum $end
$var reg 1 , carry $end
$upscope $end
$upscope $end
$enddefinitions $end
#0
0!
0"
0#
0$
U%
U&
0'
0(
0)
0*
U+
U,
#5000000
1$
0%
0&
1)
0+
0,
#10000000
1!
0$
1'
0)
#15000000
1$
1%
1)
1+
#20000000
0!
1"
0$
0'
1(
0)
#25000000
1$
1)
#30000000
1!
0$
1'
0)
#35000000
1$
0%
1&
1)
0+
1,
#40000000
0!
0"
1#
0$
0'
0(
0)
1*
#45000000
1$
1%
0&
1)
1+
0,
#50000000
1!
0$
1'
0)
#55000000
1$
0%
1&
1)
0+
1,
#60000000
1"
0$
1(
0)
#65000000
1$
1%
1)
1+
