Lab2/ripple_adder/FA.vhdl
library ieee;
use ieee.std_logic_1164.all;

entity FA is 
  port (a, b, c_in : in std_logic;
        sum, carry : out std_logic
    );
end FA;

architecture arch of FA is

begin
  sum <= a xor b xor c_in; 
  carry <= (a and b) or (c_in and a) or (c_in and b) ;
end arch;

Lab2/4bit_carry-lookahead_adder/lookahead.vhdl
library ieee;
use ieee.std_logic_1164.all;

entity lookahead_4bit_FA is 
  port (
  	a, b : in std_logic_vector (3 downto 0);
  	c_in : in std_logic;
        s : out std_logic_vector (4 downto 0)
    );
end lookahead_4bit_FA;

architecture arch of lookahead_4bit_FA is


signal G:std_logic_vector (3 downto 0);
signal P:std_logic_vector (3 downto 0);
signal c:std_logic_vector (4 downto 0);
signal sum:std_logic_vector (3 downto 0);



begin
	
	Full_adder1 : entity work.FA port map (
    		a => a(0),
    		b => b(0),
    		c_in => c(0),
		sum => sum(0),
		carry => open
		);
	Full_adder2 : entity work.FA port map (
    		a => a(1),
    		b => b(1),
    		c_in => c(1),
		sum => sum(1),
		carry => open
		);
	Full_adder3 : entity work.FA port map (
    		a => a(2),
    		b => b(2),
    		c_in => c(2),
		sum => sum(2),
		carry => open
		);
	Full_adder4 : entity work.FA port map (
    		a => a(3),
    		b => b(3),
    		c_in => c(3),
		sum => sum(3),
		carry => open
		);
		
	--Generate Vector: Gi=Ai*Bi
	
	G(0)<=a(0) and b(0);
	G(1)<=a(1) and b(1);
	G(2)<=a(3) and b(2);
	G(3)<=a(3) and b(3);
	
	--Propagate Vector: Gi=Ai+Bi
	
	P(0)<=a(0) or b(0);
	P(1)<=a(1) or b(1);
	P(2)<=a(3) or b(2);
	P(3)<=a(3) or b(3);
	
	--Carry logic
	
	c(0)<=c_in;
	c(1)<=G(0) or (P(0) and c(0));
	c(2)<=G(1) or (P(1) and c(1));
	c(3)<=G(2) or (P(2) and c(2));
	c(4)<=G(3) or (P(3) and c(3));
	
	
	s<=c(4) & sum;
end arch;

Lab2/carry_lookahead/test_bench_proc.vhdl

library ieee;
use ieee.std_logic_1164.all;
use ieee.numeric_std.all;

--In this version of TB the design
--uses 2 for-loop cycle to generate
--the A and B input of the sum



entity lookahead_tb is
end lookahead_tb;

--In the declaration we put all the
--signals we need: the input output  
--of the DUT, and a time definition
architecture tb of lookahead_tb is
    signal a, b :std_logic_vector(3 downto 0);--input
    signal c_in : std_logic:='0';  --input
    signal result : std_logic_vector(4 downto 0);  -- output
    constant period: time := 1 ns; --time constant
   
begin
        -- connecting testbench signals with half_adder.vhd
	UUT : entity work.lookahead_4bit_FA port map (
		c_in=>c_in,
		a => a,
		b => b,
		s => result
		);
process
--two concatenated for-loops generate all the addend combinations 
	begin
	for ia in 0 to 15 loop
		a<=std_logic_vector(to_unsigned(ia,4));
		for ib in 0 to 15 loop	
			b<=std_logic_vector(to_unsigned(ib,4));
			wait for period;
		end loop;
	end loop;
end process;
             
          
end tb ;

Lab2/4bit_carry-lookahead_adder/waves.vcd
$date
  Sun Nov 29 14:29:56 2020
$end
$version
  GHDL v0
$end
$timescale
  1 fs
$end
$scope module standard $end
$upscope $end
$scope module std_logic_1164 $end
$upscope $end
$scope module numeric_std $end
$upscope $end
$scope module lookahead_tb $end
$var reg 4 ! a[3:0] $end
$var reg 4 " b[3:0] $end
$var reg 1 # c_in $end
$var reg 5 $ result[4:0] $end
$scope module uut $end
$var reg 4 % a[3:0] $end
$var reg 4 & b[3:0] $end
$var reg 1 ' c_in $end
$var reg 5 ( s[4:0] $end
$var reg 4 ) g[3:0] $end
$var reg 4 * p[3:0] $end
$var reg 5 + c[4:0] $end
$var reg 4 , sum[3:0] $end
$scope module full_adder1 $end
$var reg 1 - a $end
$var reg 1 . b $end
$var reg 1 / c_in $end
$var reg 1 0 sum $end
$var reg 1 1 carry $end
$upscope $end
$scope module full_adder2 $end
$var reg 1 2 a $end
$var reg 1 3 b $end
$var reg 1 4 c_in $end
$var reg 1 5 sum $end
$var reg 1 6 carry $end
$upscope $end
$scope module full_adder3 $end
$var reg 1 7 a $end
$var reg 1 8 b $end
$var reg 1 9 c_in $end
$var reg 1 : sum $end
$var reg 1 ; carry $end
$upscope $end
$scope module full_adder4 $end
$var reg 1 < a $end
$var reg 1 = b $end
$var reg 1 > c_in $end
$var reg 1 ? sum $end
$var reg 1 @ carry $end
$upscope $end
$upscope $end
$upscope $end
$enddefinitions $end
#0
b0000 !
b0000 "
0#
b00000 $
b0000 %
b0000 &
0'
b00000 (
b0000 )
b0000 *
b00000 +
b0000 ,
0-
0.
0/
00
01
02
03
04
05
06
07
08
09
0:
0;
0<
0=
0>
0?
0@
#1000000
b0001 "
b00001 $
b0001 &
b00001 (
b0001 *
b0001 ,
1.
10
#2000000
b0010 "
b00010 $
b0010 &
b00010 (
b0010 *
b0010 ,
0.
00
13
15
#3000000
b0011 "
b00011 $
b0011 &
b00011 (
b0011 *
b0011 ,
1.
10
#4000000
b0100 "
b00100 $
b0100 &
b00100 (
b0100 *
b0100 ,
0.
00
03
05
18
1:
#5000000
b0101 "
b00101 $
b0101 &
b00101 (
b0101 *
b0101 ,
1.
10
#6000000
b0110 "
b00110 $
b0110 &
b00110 (
b0110 *
b0110 ,
0.
00
13
15
#7000000
b0111 "
b00111 $
b0111 &
b00111 (
b0111 *
b0111 ,
1.
10
#8000000
b1000 "
b01000 $
b1000 &
b01000 (
b1000 *
b1000 ,
0.
00
03
05
08
0:
1=
1?
#9000000
b1001 "
b01001 $
b1001 &
b01001 (
b1001 *
b1001 ,
1.
10
#10000000
b1010 "
b01010 $
b1010 &
b01010 (
b1010 *
b1010 ,
0.
00
13
15
#11000000
b1011 "
b01011 $
b1011 &
b01011 (
b1011 *
b1011 ,
1.
10
#12000000
b1100 "
b01100 $
b1100 &
b01100 (
b1100 *
b1100 ,
0.
00
03
05
18
1:
#13000000
b1101 "
b01101 $
b1101 &
b01101 (
b1101 *
b1101 ,
1.
10
#14000000
b1110 "
b01110 $
b1110 &
b01110 (
b1110 *
b1110 ,
0.
00
13
15
#15000000
b1111 "
b01111 $
b1111 &
b01111 (
b1111 *
b1111 ,
1.
10
#16000000
b0001 !
b0000 "
b00001 $
b0001 %
b0000 &
b00001 (
b0001 *
b0001 ,
1-
0.
03
05
08
0:
0=
0?
#17000000
b0001 "
b00010 $
b0001 &
b00010 (
b0001 )
b00010 +
b0010 ,
1.
00
11
14
15
#18000000
b0010 "
b00011 $
b0010 &
b00011 (
b0000 )
b0011 *
b00000 +
b0011 ,
0.
10
01
13
04
15
06
09
0:
#19000000
b0011 "
b00100 $
b0011 &
b00100 (
b0001 )
b00110 +
b0100 ,
1.
00
11
14
05
16
19
1:
#20000000
b0100 "
b00101 $
b0100 &
b00101 (
b0000 )
b0101 *
b00000 +
b0101 ,
0.
10
01
03
04
05
06
18
09
1:
0;
0>
0?
#21000000
b0101 "
b00110 $
b0101 &
b00110 (
b0001 )
b00010 +
b0110 ,
1.
00
11
14
15
#22000000
b0110 "
b00111 $
b0110 &
b00111 (
b0000 )
b0111 *
b00000 +
b0111 ,
0.
10
01
13
04
15
06
09
1:
0;
0>
0?
#23000000
b0111 "
b01000 $
b0111 &
b01000 (
b0001 )
b01110 +
b1000 ,
1.
00
11
14
05
16
19
0:
1;
1>
1?
#24000000
b1000 "
b01001 $
b1000 &
b01001 (
b0000 )
b1001 *
b00000 +
b1001 ,
0.
10
01
03
04
05
06
08
09
0:
0;
1=
0>
1?
0@
#25000000
b1001 "
b01010 $
b1001 &
b01010 (
b0001 )
b00010 +
b1010 ,
1.
00
11
14
15
#26000000
b1010 "
b01011 $
b1010 &
b01011 (
b0000 )
b1011 *
b00000 +
b1011 ,
0.
10
01
13
04
15
06
09
0:
#27000000
b1011 "
b01100 $
b1011 &
b01100 (
b0001 )
b00110 +
b1100 ,
1.
00
11
14
05
16
19
1:
#28000000
b1100 "
b01101 $
b1100 &
b01101 (
b0000 )
b1101 *
b00000 +
b1101 ,
0.
10
01
03
04
05
06
18
09
1:
0;
0>
1?
0@
#29000000
b1101 "
b01110 $
b1101 &
b01110 (
b0001 )
b00010 +
b1110 ,
1.
00
11
14
15
#30000000
b1110 "
b01111 $
b1110 &
b01111 (
b0000 )
b1111 *
b00000 +
b1111 ,
0.
10
01
13
04
15
06
09
1:
0;
0>
1?
0@
#31000000
b1111 "
b10000 $
b1111 &
b10000 (
b0001 )
b11110 +
b0000 ,
1.
00
11
14
05
16
19
0:
1;
1>
0?
1@
#32000000
b0010 !
b0000 "
b00010 $
b0010 %
b0000 &
b00010 (
b0000 )
b0010 *
b00000 +
b0010 ,
0-
0.
01
12
03
04
15
06
08
09
0:
0;
0=
0>
0?
0@
#33000000
b0001 "
b00011 $
b0001 &
b00011 (
b0011 *
b0011 ,
1.
10
#34000000
b0010 "
b00100 $
b0010 &
b00100 (
b0010 )
b0010 *
b00100 +
b0100 ,
0.
00
13
05
16
19
1:
#35000000
b0011 "
b00101 $
b0011 &
b00101 (
b0011 *
b0101 ,
1.
10
#36000000
b0100 "
b00110 $
b0100 &
b00110 (
b0000 )
b0110 *
b00000 +
b0110 ,
0.
00
03
15
06
18
09
1:
0;
0>
0?
#37000000
b0101 "
b00111 $
b0101 &
b00111 (
b0111 *
b0111 ,
1.
10
#38000000
b0110 "
b01000 $
b0110 &
b01000 (
b0010 )
b0110 *
b01100 +
b1000 ,
0.
00
13
05
16
19
0:
1;
1>
1?
#39000000
b0111 "
b01001 $
b0111 &
b01001 (
b0111 *
b1001 ,
1.
10
#40000000
b1000 "
b01010 $
b1000 &
b01010 (
b0000 )
b1010 *
b00000 +
b1010 ,
0.
00
03
15
06
08
09
0:
0;
1=
0>
1?
0@
#41000000
b1001 "
b01011 $
b1001 &
b01011 (
b1011 *
b1011 ,
1.
10
#42000000
b1010 "
b01100 $
b1010 &
b01100 (
b0010 )
b1010 *
b00100 +
b1100 ,
0.
00
13
05
16
19
1:
#43000000
b1011 "
b01101 $
b1011 &
b01101 (
b1011 *
b1101 ,
1.
10
#44000000
b1100 "
b01110 $
b1100 &
b01110 (
b0000 )
b1110 *
b00000 +
b1110 ,
0.
00
03
15
06
18
09
1:
0;
0>
1?
0@
#45000000
b1101 "
b01111 $
b1101 &
b01111 (
b1111 *
b1111 ,
1.
10
#46000000
b1110 "
b10000 $
b1110 &
b10000 (
b0010 )
b1110 *
b11100 +
b0000 ,
0.
00
13
05
16
19
0:
1;
1>
0?
1@
#47000000
b1111 "
b10001 $
b1111 &
b10001 (
b1111 *
b0001 ,
1.
10
#48000000
b0011 !
b0000 "
b00011 $
b0011 %
b0000 &
b00011 (
b0000 )
b0011 *
b00000 +
b0011 ,
1-
0.
03
15
06
08
09
0:
0;
0=
0>
0?
0@
#49000000
b0001 "
b00100 $
b0001 &
b00100 (
b0001 )
b00110 +
b0100 ,
1.
00
11
14
05
16
19
1:
#50000000
b0010 "
b00101 $
b0010 &
b00101 (
b0010 )
b00100 +
b0101 ,
0.
10
01
13
04
05
#51000000
b0011 "
b00110 $
b0011 &
b00110 (
b0011 )
b00110 +
b0110 ,
1.
00
11
14
15
#52000000
b0100 "
b00111 $
b0100 &
b00111 (
b0000 )
b0111 *
b00000 +
b0111 ,
0.
10
01
03
04
15
06
18
09
1:
0;
0>
0?
#53000000
b0101 "
b01000 $
b0101 &
b01000 (
b0001 )
b01110 +
b1000 ,
1.
00
11
14
05
16
19
0:
1;
1>
1?
#54000000
b0110 "
b01001 $
b0110 &
b01001 (
b0010 )
b01100 +
b1001 ,
0.
10
01
13
04
05
#55000000
b0111 "
b01010 $
b0111 &
b01010 (
b0011 )
b01110 +
b1010 ,
1.
00
11
14
15
#56000000
b1000 "
b01011 $
b1000 &
b01011 (
b0000 )
b1011 *
b00000 +
b1011 ,
0.
10
01
03
04
15
06
08
09
0:
0;
1=
0>
1?
0@
#57000000
b1001 "
b01100 $
b1001 &
b01100 (
b0001 )
b00110 +
b1100 ,
1.
00
11
14
05
16
19
1:
#58000000
b1010 "
b01101 $
b1010 &
b01101 (
b0010 )
b00100 +
b1101 ,
0.
10
01
13
04
05
#59000000
b1011 "
b01110 $
b1011 &
b01110 (
b0011 )
b00110 +
b1110 ,
1.
00
11
14
15
#60000000
b1100 "
b01111 $
b1100 &
b01111 (
b0000 )
b1111 *
b00000 +
b1111 ,
0.
10
01
03
04
15
06
18
09
1:
0;
0>
1?
0@
#61000000
b1101 "
b10000 $
b1101 &
b10000 (
b0001 )
b11110 +
b0000 ,
1.
00
11
14
05
16
19
0:
1;
1>
0?
1@
#62000000
b1110 "
b10001 $
b1110 &
b10001 (
b0010 )
b11100 +
b0001 ,
0.
10
01
13
04
05
#63000000
b1111 "
b10010 $
b1111 &
b10010 (
b0011 )
b11110 +
b0010 ,
1.
00
11
14
15
#64000000
b0100 !
b0000 "
b00100 $
b0100 %
b0000 &
b00100 (
b0000 )
b0000 *
b00000 +
b0100 ,
0-
0.
01
02
03
04
05
06
17
08
09
1:
0;
0=
0>
0?
0@
#65000000
b0001 "
b00101 $
b0001 &
b00101 (
b0001 *
b0101 ,
1.
10
#66000000
b0010 "
b00110 $
b0010 &
b00110 (
b0010 *
b0110 ,
0.
00
13
15
#67000000
b0011 "
b00111 $
b0011 &
b00111 (
b0011 *
b0111 ,
1.
10
#68000000
b0100 "
b00000 $
b0100 &
b00000 (
b0100 *
b0000 ,
0.
00
03
05
18
0:
1;
#69000000
b0101 "
b00001 $
b0101 &
b00001 (
b0101 *
b0001 ,
1.
10
#70000000
b0110 "
b00010 $
b0110 &
b00010 (
b0110 *
b0010 ,
0.
00
13
15
#71000000
b0111 "
b00011 $
b0111 &
b00011 (
b0111 *
b0011 ,
1.
10
#72000000
b1000 "
b01100 $
b1000 &
b01100 (
b1000 *
b1100 ,
0.
00
03
05
08
1:
0;
1=
1?
#73000000
b1001 "
b01101 $
b1001 &
b01101 (
b1001 *
b1101 ,
1.
10
#74000000
b1010 "
b01110 $
b1010 &
b01110 (
b1010 *
b1110 ,
0.
00
13
15
#75000000
b1011 "
b01111 $
b1011 &
b01111 (
b1011 *
b1111 ,
1.
10
#76000000
b1100 "
b01000 $
b1100 &
b01000 (
b1100 *
b1000 ,
0.
00
03
05
18
0:
1;
#77000000
b1101 "
b01001 $
b1101 &
b01001 (
b1101 *
b1001 ,
1.
10
#78000000
b1110 "
b01010 $
b1110 &
b01010 (
b1110 *
b1010 ,
0.
00
13
15
#79000000
b1111 "
b01011 $
b1111 &
b01011 (
b1111 *
b1011 ,
1.
10
#80000000
b0101 !
b0000 "
b00101 $
b0101 %
b0000 &
b00101 (
b0001 *
b0101 ,
1-
0.
03
05
08
1:
0;
0=
0?
#81000000
b0001 "
b00110 $
b0001 &
b00110 (
b0001 )
b00010 +
b0110 ,
1.
00
11
14
15
#82000000
b0010 "
b00111 $
b0010 &
b00111 (
b0000 )
b0011 *
b00000 +
b0111 ,
0.
10
01
13
04
15
06
09
1:
0;
#83000000
b0011 "
b00000 $
b0011 &
b00000 (
b0001 )
b00110 +
b0000 ,
1.
00
11
14
05
16
19
0:
1;
#84000000
b0100 "
b00001 $
b0100 &
b00001 (
b0000 )
b0101 *
b00000 +
b0001 ,
0.
10
01
03
04
05
06
18
09
0:
0>
0?
#85000000
b0101 "
b00010 $
b0101 &
b00010 (
b0001 )
b00010 +
b0010 ,
1.
00
11
14
15
#86000000
b0110 "
b00011 $
b0110 &
b00011 (
b0000 )
b0111 *
b00000 +
b0011 ,
0.
10
01
13
04
15
06
09
0:
0>
0?
#87000000
b0111 "
b01100 $
b0111 &
b01100 (
b0001 )
b01110 +
b1100 ,
1.
00
11
14
05
16
19
1:
1>
1?
#88000000
b1000 "
b01101 $
b1000 &
b01101 (
b0000 )
b1001 *
b00000 +
b1101 ,
0.
10
01
03
04
05
06
08
09
1:
0;
1=
0>
1?
0@
#89000000
b1001 "
b01110 $
b1001 &
b01110 (
b0001 )
b00010 +
b1110 ,
1.
00
11
14
15
#90000000
b1010 "
b01111 $
b1010 &
b01111 (
b0000 )
b1011 *
b00000 +
b1111 ,
0.
10
01
13
04
15
06
09
1:
0;
#91000000
b1011 "
b01000 $
b1011 &
b01000 (
b0001 )
b00110 +
b1000 ,
1.
00
11
14
05
16
19
0:
1;
#92000000
b1100 "
b01001 $
b1100 &
b01001 (
b0000 )
b1101 *
b00000 +
b1001 ,
0.
10
01
03
04
05
06
18
09
0:
0>
1?
0@
#93000000
b1101 "
b01010 $
b1101 &
b01010 (
b0001 )
b00010 +
b1010 ,
1.
00
11
14
15
#94000000
b1110 "
b01011 $
b1110 &
b01011 (
b0000 )
b1111 *
b00000 +
b1011 ,
0.
10
01
13
04
15
06
09
0:
0>
1?
0@
#95000000
b1111 "
b10100 $
b1111 &
b10100 (
b0001 )
b11110 +
b0100 ,
1.
00
11
14
05
16
19
1:
1>
0?
1@
#96000000
b0110 !
b0000 "
b00110 $
b0110 %
b0000 &
b00110 (
b0000 )
b0010 *
b00000 +
b0110 ,
0-
0.
01
12
03
04
15
06
08
09
1:
0;
0=
0>
0?
0@
#97000000
b0001 "
b00111 $
b0001 &
b00111 (
b0011 *
b0111 ,
1.
10
#98000000
b0010 "
b00000 $
b0010 &
b00000 (
b0010 )
b0010 *
b00100 +
b0000 ,
0.
00
13
05
16
19
0:
1;
#99000000
b0011 "
b00001 $
b0011 &
b00001 (
b0011 *
b0001 ,
1.
10
#100000000
b0100 "
b00010 $
b0100 &
b00010 (
b0000 )
b0110 *
b00000 +
b0010 ,
0.
00
03
15
06
18
09
0:
0>
0?
#101000000
b0101 "
b00011 $
b0101 &
b00011 (
b0111 *
b0011 ,
1.
10
#102000000
b0110 "
b01100 $
b0110 &
b01100 (
b0010 )
b0110 *
b01100 +
b1100 ,
0.
00
13
05
16
19
1:
1>
1?
#103000000
b0111 "
b01101 $
b0111 &
b01101 (
b0111 *
b1101 ,
1.
10
#104000000
b1000 "
b01110 $
b1000 &
b01110 (
b0000 )
b1010 *
b00000 +
b1110 ,
0.
00
03
15
06
08
09
1:
0;
1=
0>
1?
0@
#105000000
b1001 "
b01111 $
b1001 &
b01111 (
b1011 *
b1111 ,
1.
10
#106000000
b1010 "
b01000 $
b1010 &
b01000 (
b0010 )
b1010 *
b00100 +
b1000 ,
0.
00
13
05
16
19
0:
1;
#107000000
b1011 "
b01001 $
b1011 &
b01001 (
b1011 *
b1001 ,
1.
10
#108000000
b1100 "
b01010 $
b1100 &
b01010 (
b0000 )
b1110 *
b00000 +
b1010 ,
0.
00
03
15
06
18
09
0:
0>
1?
0@
#109000000
b1101 "
b01011 $
b1101 &
b01011 (
b1111 *
b1011 ,
1.
10
#110000000
b1110 "
b10100 $
b1110 &
b10100 (
b0010 )
b1110 *
b11100 +
b0100 ,
0.
00
13
05
16
19
1:
1>
0?
1@
#111000000
b1111 "
b10101 $
b1111 &
b10101 (
b1111 *
b0101 ,
1.
10
#112000000
b0111 !
b0000 "
b00111 $
b0111 %
b0000 &
b00111 (
b0000 )
b0011 *
b00000 +
b0111 ,
1-
0.
03
15
06
08
09
1:
0;
0=
0>
0?
0@
#113000000
b0001 "
b00000 $
b0001 &
b00000 (
b0001 )
b00110 +
b0000 ,
1.
00
11
14
05
16
19
0:
1;
#114000000
b0010 "
b00001 $
b0010 &
b00001 (
b0010 )
b00100 +
b0001 ,
0.
10
01
13
04
05
#115000000
b0011 "
b00010 $
b0011 &
b00010 (
b0011 )
b00110 +
b0010 ,
1.
00
11
14
15
#116000000
b0100 "
b00011 $
b0100 &
b00011 (
b0000 )
b0111 *
b00000 +
b0011 ,
0.
10
01
03
04
15
06
18
09
0:
0>
0?
#117000000
b0101 "
b01100 $
b0101 &
b01100 (
b0001 )
b01110 +
b1100 ,
1.
00
11
14
05
16
19
1:
1>
1?
#118000000
b0110 "
b01101 $
b0110 &
b01101 (
b0010 )
b01100 +
b1101 ,
0.
10
01
13
04
05
#119000000
b0111 "
b01110 $
b0111 &
b01110 (
b0011 )
b01110 +
b1110 ,
1.
00
11
14
15
#120000000
b1000 "
b01111 $
b1000 &
b01111 (
b0000 )
b1011 *
b00000 +
b1111 ,
0.
10
01
03
04
15
06
08
09
1:
0;
1=
0>
1?
0@
#121000000
b1001 "
b01000 $
b1001 &
b01000 (
b0001 )
b00110 +
b1000 ,
1.
00
11
14
05
16
19
0:
1;
#122000000
b1010 "
b01001 $
b1010 &
b01001 (
b0010 )
b00100 +
b1001 ,
0.
10
01
13
04
05
#123000000
b1011 "
b01010 $
b1011 &
b01010 (
b0011 )
b00110 +
b1010 ,
1.
00
11
14
15
#124000000
b1100 "
b01011 $
b1100 &
b01011 (
b0000 )
b1111 *
b00000 +
b1011 ,
0.
10
01
03
04
15
06
18
09
0:
0>
1?
0@
#125000000
b1101 "
b10100 $
b1101 &
b10100 (
b0001 )
b11110 +
b0100 ,
1.
00
11
14
05
16
19
1:
1>
0?
1@
#126000000
b1110 "
b10101 $
b1110 &
b10101 (
b0010 )
b11100 +
b0101 ,
0.
10
01
13
04
05
#127000000
b1111 "
b10110 $
b1111 &
b10110 (
b0011 )
b11110 +
b0110 ,
1.
00
11
14
15
#128000000
b1000 !
b0000 "
b01000 $
b1000 %
b0000 &
b01000 (
b0000 )
b1100 *
b00000 +
b1000 ,
0-
0.
01
02
03
04
05
06
07
08
09
0:
0;
1<
0=
0>
1?
0@
#129000000
b0001 "
b01001 $
b0001 &
b01001 (
b1101 *
b1001 ,
1.
10
#130000000
b0010 "
b01010 $
b0010 &
b01010 (
b1110 *
b1010 ,
0.
00
13
15
#131000000
b0011 "
b01011 $
b0011 &
b01011 (
b1111 *
b1011 ,
1.
10
#132000000
b0100 "
b10100 $
b0100 &
b10100 (
b0100 )
b1100 *
b11000 +
b0100 ,
0.
00
03
05
18
1:
1>
0?
1@
#133000000
b0101 "
b10101 $
b0101 &
b10101 (
b1101 *
b0101 ,
1.
10
#134000000
b0110 "
b10110 $
b0110 &
b10110 (
b1110 *
b0110 ,
0.
00
13
15
#135000000
b0111 "
b10111 $
b0111 &
b10111 (
b1111 *
b0111 ,
1.
10
#136000000
b1000 "
b10000 $
b1000 &
b10000 (
b1000 )
b1100 *
b10000 +
b0000 ,
0.
00
03
05
08
0:
1=
0>
0?
#137000000
b1001 "
b10001 $
b1001 &
b10001 (
b1101 *
b0001 ,
1.
10
#138000000
b1010 "
b10010 $
b1010 &
b10010 (
b1110 *
b0010 ,
0.
00
13
15
#139000000
b1011 "
b10011 $
b1011 &
b10011 (
b1111 *
b0011 ,
1.
10
#140000000
b1100 "
b11100 $
b1100 &
b11100 (
b1100 )
b1100 *
b11000 +
b1100 ,
0.
00
03
05
18
1:
1>
1?
#141000000
b1101 "
b11101 $
b1101 &
b11101 (
b1101 *
b1101 ,
1.
10
#142000000
b1110 "
b11110 $
b1110 &
b11110 (
b1110 *
b1110 ,
0.
00
13
15
#143000000
b1111 "
b11111 $
b1111 &
b11111 (
b1111 *
b1111 ,
1.
10
#144000000
b1001 !
b0000 "
b01001 $
b1001 %
b0000 &
b01001 (
b0000 )
b1101 *
b00000 +
b1001 ,
1-
0.
03
05
08
0:
0=
0>
1?
0@
#145000000
b0001 "
b01010 $
b0001 &
b01010 (
b0001 )
b00010 +
b1010 ,
1.
00
11
14
15
#146000000
b0010 "
b01011 $
b0010 &
b01011 (
b0000 )
b1111 *
b00000 +
b1011 ,
0.
10
01
13
04
15
06
09
0:
0>
1?
0@
#147000000
b0011 "
b10100 $
b0011 &
b10100 (
b0001 )
b11110 +
b0100 ,
1.
00
11
14
05
16
19
1:
1>
0?
1@
#148000000
b0100 "
b10101 $
b0100 &
b10101 (
b0100 )
b1101 *
b11000 +
b0101 ,
0.
10
01
03
04
05
06
18
09
1:
0;
#149000000
b0101 "
b10110 $
b0101 &
b10110 (
b0101 )
b11010 +
b0110 ,
1.
00
11
14
15
#150000000
b0110 "
b10111 $
b0110 &
b10111 (
b0100 )
b1111 *
b11000 +
b0111 ,
0.
10
01
13
04
15
06
09
1:
0;
#151000000
b0111 "
b10000 $
b0111 &
b10000 (
b0101 )
b11110 +
b0000 ,
1.
00
11
14
05
16
19
0:
1;
#152000000
b1000 "
b10001 $
b1000 &
b10001 (
b1000 )
b1101 *
b10000 +
b0001 ,
0.
10
01
03
04
05
06
08
09
0:
0;
1=
0>
0?
#153000000
b1001 "
b10010 $
b1001 &
b10010 (
b1001 )
b10010 +
b0010 ,
1.
00
11
14
15
#154000000
b1010 "
b10011 $
b1010 &
b10011 (
b1000 )
b1111 *
b10000 +
b0011 ,
0.
10
01
13
04
15
06
09
0:
0>
0?
#155000000
b1011 "
b11100 $
b1011 &
b11100 (
b1001 )
b11110 +
b1100 ,
1.
00
11
14
05
16
19
1:
1>
1?
#156000000
b1100 "
b11101 $
b1100 &
b11101 (
b1100 )
b1101 *
b11000 +
b1101 ,
0.
10
01
03
04
05
06
18
09
1:
0;
#157000000
b1101 "
b11110 $
b1101 &
b11110 (
b1101 )
b11010 +
b1110 ,
1.
00
11
14
15
#158000000
b1110 "
b11111 $
b1110 &
b11111 (
b1100 )
b1111 *
b11000 +
b1111 ,
0.
10
01
13
04
15
06
09
1:
0;
#159000000
b1111 "
b11000 $
b1111 &
b11000 (
b1101 )
b11110 +
b1000 ,
1.
00
11
14
05
16
19
0:
1;
#160000000
b1010 !
b0000 "
b01010 $
b1010 %
b0000 &
b01010 (
b0000 )
b1110 *
b00000 +
b1010 ,
0-
0.
01
12
03
04
15
06
08
09
0:
0;
0=
0>
1?
0@
#161000000
b0001 "
b01011 $
b0001 &
b01011 (
b1111 *
b1011 ,
1.
10
#162000000
b0010 "
b10100 $
b0010 &
b10100 (
b0010 )
b1110 *
b11100 +
b0100 ,
0.
00
13
05
16
19
1:
1>
0?
1@
#163000000
b0011 "
b10101 $
b0011 &
b10101 (
b1111 *
b0101 ,
1.
10
#164000000
b0100 "
b10110 $
b0100 &
b10110 (
b0100 )
b1110 *
b11000 +
b0110 ,
0.
00
03
15
06
18
09
1:
0;
#165000000
b0101 "
b10111 $
b0101 &
b10111 (
b1111 *
b0111 ,
1.
10
#166000000
b0110 "
b10000 $
b0110 &
b10000 (
b0110 )
b1110 *
b11100 +
b0000 ,
0.
00
13
05
16
19
0:
1;
#167000000
b0111 "
b10001 $
b0111 &
b10001 (
b1111 *
b0001 ,
1.
10
#168000000
b1000 "
b10010 $
b1000 &
b10010 (
b1000 )
b1110 *
b10000 +
b0010 ,
0.
00
03
15
06
08
09
0:
0;
1=
0>
0?
#169000000
b1001 "
b10011 $
b1001 &
b10011 (
b1111 *
b0011 ,
1.
10
#170000000
b1010 "
b11100 $
b1010 &
b11100 (
b1010 )
b1110 *
b11100 +
b1100 ,
0.
00
13
05
16
19
1:
1>
1?
#171000000
b1011 "
b11101 $
b1011 &
b11101 (
b1111 *
b1101 ,
1.
10
#172000000
b1100 "
b11110 $
b1100 &
b11110 (
b1100 )
b1110 *
b11000 +
b1110 ,
0.
00
03
15
06
18
09
1:
0;
#173000000
b1101 "
b11111 $
b1101 &
b11111 (
b1111 *
b1111 ,
1.
10
#174000000
b1110 "
b11000 $
b1110 &
b11000 (
b1110 )
b1110 *
b11100 +
b1000 ,
0.
00
13
05
16
19
0:
1;
#175000000
b1111 "
b11001 $
b1111 &
b11001 (
b1111 *
b1001 ,
1.
10
#176000000
b1011 !
b0000 "
b01011 $
b1011 %
b0000 &
b01011 (
b0000 )
b00000 +
b1011 ,
1-
0.
03
15
06
08
09
0:
0;
0=
0>
1?
0@
#177000000
b0001 "
b10100 $
b0001 &
b10100 (
b0001 )
b11110 +
b0100 ,
1.
00
11
14
05
16
19
1:
1>
0?
1@
#178000000
b0010 "
b10101 $
b0010 &
b10101 (
b0010 )
b11100 +
b0101 ,
0.
10
01
13
04
05
#179000000
b0011 "
b10110 $
b0011 &
b10110 (
b0011 )
b11110 +
b0110 ,
1.
00
11
14
15
#180000000
b0100 "
b10111 $
b0100 &
b10111 (
b0100 )
b11000 +
b0111 ,
0.
10
01
03
04
15
06
18
09
1:
0;
#181000000
b0101 "
b10000 $
b0101 &
b10000 (
b0101 )
b11110 +
b0000 ,
1.
00
11
14
05
16
19
0:
1;
#182000000
b0110 "
b10001 $
b0110 &
b10001 (
b0110 )
b11100 +
b0001 ,
0.
10
01
13
04
05
#183000000
b0111 "
b10010 $
b0111 &
b10010 (
b0111 )
b11110 +
b0010 ,
1.
00
11
14
15
#184000000
b1000 "
b10011 $
b1000 &
b10011 (
b1000 )
b10000 +
b0011 ,
0.
10
01
03
04
15
06
08
09
0:
0;
1=
0>
0?
#185000000
b1001 "
b11100 $
b1001 &
b11100 (
b1001 )
b11110 +
b1100 ,
1.
00
11
14
05
16
19
1:
1>
1?
#186000000
b1010 "
b11101 $
b1010 &
b11101 (
b1010 )
b11100 +
b1101 ,
0.
10
01
13
04
05
#187000000
b1011 "
b11110 $
b1011 &
b11110 (
b1011 )
b11110 +
b1110 ,
1.
00
11
14
15
#188000000
b1100 "
b11111 $
b1100 &
b11111 (
b1100 )
b11000 +
b1111 ,
0.
10
01
03
04
15
06
18
09
1:
0;
#189000000
b1101 "
b11000 $
b1101 &
b11000 (
b1101 )
b11110 +
b1000 ,
1.
00
11
14
05
16
19
0:
1;
#190000000
b1110 "
b11001 $
b1110 &
b11001 (
b1110 )
b11100 +
b1001 ,
0.
10
01
13
04
05
#191000000
b1111 "
b11010 $
b1111 &
b11010 (
b1111 )
b11110 +
b1010 ,
1.
00
11
14
15
#192000000
b1100 !
b0000 "
b01100 $
b1100 %
b0000 &
b01100 (
b0000 )
b1100 *
b00000 +
b1100 ,
0-
0.
01
02
03
04
05
06
17
08
09
1:
0;
0=
0>
1?
0@
#193000000
b0001 "
b01101 $
b0001 &
b01101 (
b1101 *
b1101 ,
1.
10
